Metadata-Version: 1.0
Name: nearest-square
Version: 1.1
Summary: Nearest Square
Home-page: UNKNOWN
Author: Rahul Gupta
Author-email: 385.rahul@gmail.com
License: UNKNOWN
Platform: UNKNOWN
